writhub/__init__.py
writhub/cli.py
writhub/collaters/__init__.py
writhub/collaters/collater.py
writhub/collaters/md.py
writhub/errors.py
writhub/mylog.py
writhub/settings.py
writhub/writhub.py
writhub-0.0.1.dist-info/entry_points.txt
writhub-0.0.1.dist-info/WHEEL
writhub-0.0.1.dist-info/METADATA
writhub-0.0.1.dist-info/RECORD
